{
  "run_name": "tiny_cnn_20260405_184223_219d036188e6",
  "config_hash": "219d036188e6",
  "dataset_dir": "D:\\Codes\\Quantum\\DriftAdaptiveQEC\\artifacts\\datasets\\runtime_b_residual_no_teacher_params_v1",
  "dataset_manifest": {
    "config_hash": "51db70f8c56a",
    "config_path": "/Users/qinchaoyang/Desktop/PC/codes/local/quantum/DriftAdaptiveQEC/cnn_fpga/config/experiment_runtime_b_residual_no_teacher_params.yaml",
    "dataset_dir": "/Users/qinchaoyang/Desktop/PC/codes/local/quantum/DriftAdaptiveQEC/artifacts/datasets/runtime_b_residual_no_teacher_params_v1",
    "reference_mode": "static_linear",
    "teacher_mode": "window_variance",
    "label_semantics": "residual_b",
    "context_windows": 5,
    "context_padding": "edge_repeat",
    "include_histogram_deltas": true,
    "include_teacher_prediction": true,
    "include_teacher_params": false,
    "include_teacher_deltas": true,
    "windows_per_scenario": 512,
    "n_samples_total": 2048,
    "histogram_shape": [
      19,
      32,
      32
    ],
    "input_channel_names": [
      "hist_t-4",
      "hist_t-3",
      "hist_t-2",
      "hist_t-1",
      "hist_t",
      "hist_delta_t-3_minus_t-4",
      "hist_delta_t-2_minus_t-3",
      "hist_delta_t-1_minus_t-2",
      "hist_delta_t_minus_t-1",
      "teacher_sigma",
      "teacher_mu_q",
      "teacher_mu_p",
      "teacher_theta_deg",
      "teacher_delta_sigma",
      "teacher_delta_mu_q",
      "teacher_delta_mu_p",
      "teacher_delta_theta_deg",
      "teacher_delta_b_q",
      "teacher_delta_b_p"
    ],
    "label_names": [
      "b_q",
      "b_p"
    ],
    "teacher_label_names": [
      "sigma",
      "mu_q",
      "mu_p",
      "theta_deg"
    ],
    "teacher_runtime_param_names": [
      "b_q",
      "b_p"
    ],
    "n_train": 1638,
    "n_val": 204,
    "n_test": 206,
    "scenarios": [
      "static_bias_theta",
      "linear_ramp",
      "step_sigma_theta",
      "periodic_drift"
    ],
    "split": {
      "train": 0.8,
      "val": 0.1,
      "test": 0.1
    },
    "label_stats": {
      "train": {
        "mean": [
          0.002265887800604105,
          -0.0025596939958631992
        ],
        "std": [
          0.0016187616856768727,
          0.0017658600118011236
        ],
        "min": [
          -0.0010269744088873267,
          -0.007552150171250105
        ],
        "max": [
          0.0055678836070001125,
          0.0015661435900256038
        ]
      },
      "val": {
        "mean": [
          0.0023731128312647343,
          -0.0026607373729348183
        ],
        "std": [
          0.0016940687783062458,
          0.0017939774552360177
        ],
        "min": [
          -0.0007888372638262808,
          -0.007199187763035297
        ],
        "max": [
          0.005137473810464144,
          0.0007620542892254889
        ]
      },
      "test": {
        "mean": [
          0.0022523042280226946,
          -0.002555465791374445
        ],
        "std": [
          0.001612951746210456,
          0.0017317734891548753
        ],
        "min": [
          -0.0007261022692546248,
          -0.006795874331146479
        ],
        "max": [
          0.00498460466042161,
          0.0010673123179003596
        ]
      },
      "all": {
        "mean": [
          0.002275204285979271,
          -0.0025693324860185385
        ],
        "std": [
          0.001626168261282146,
          0.001765550347045064
        ],
        "min": [
          -0.0010269744088873267,
          -0.007552150171250105
        ],
        "max": [
          0.0055678836070001125,
          0.0015661435900256038
        ]
      }
    },
    "files": {
      "train": "/Users/qinchaoyang/Desktop/PC/codes/local/quantum/DriftAdaptiveQEC/artifacts/datasets/runtime_b_residual_no_teacher_params_v1/train.npz",
      "val": "/Users/qinchaoyang/Desktop/PC/codes/local/quantum/DriftAdaptiveQEC/artifacts/datasets/runtime_b_residual_no_teacher_params_v1/val.npz",
      "test": "/Users/qinchaoyang/Desktop/PC/codes/local/quantum/DriftAdaptiveQEC/artifacts/datasets/runtime_b_residual_no_teacher_params_v1/test.npz"
    }
  },
  "model_path": "D:\\Codes\\Quantum\\DriftAdaptiveQEC\\runs\\p4_no_teacher_params_stability\\stability_20260405_184204\\generated\\seed_20260405\\hybrid_no_teacher_params\\models\\tiny_cnn_20260405_184223_219d036188e6.npz",
  "model_type": "tiny_cnn",
  "train_split": "train",
  "val_split": "val",
  "n_train": 1638,
  "n_val": 204,
  "training_backend": "torch",
  "training_device": "cuda",
  "train_metrics": {
    "mse": 2.0705404369019517e-06,
    "mae": 0.001268999150316939,
    "r2_mean": 0.2654397826063186,
    "per_label": {
      "b_q": {
        "mse": 2.3159034753647715e-06,
        "mae": 0.0013348305606851038,
        "r2": 0.11619816632377111
      },
      "b_p": {
        "mse": 1.825177398439132e-06,
        "mae": 0.0012031677399487743,
        "r2": 0.4146813988888661
      }
    }
  },
  "val_metrics": {
    "mse": 2.476953781064679e-06,
    "mae": 0.0014014744724023564,
    "r2_mean": 0.17991789059136926,
    "per_label": {
      "b_q": {
        "mse": 2.674162771741593e-06,
        "mae": 0.0014518490930541916,
        "r2": 0.06819293265166826
      },
      "b_p": {
        "mse": 2.2797447903877645e-06,
        "mae": 0.0013510998517505214,
        "r2": 0.29164284853107025
      }
    }
  },
  "tiny_cnn": {
    "conv_channels": 16,
    "kernel_size": 3,
    "hidden_dim": 96,
    "batch_size": 64,
    "epochs": 36,
    "learning_rate": 0.002,
    "weight_decay": 0.0001,
    "patience": 8,
    "backend": "torch",
    "device": "auto",
    "label_weights": {
      "b_q": 2.0,
      "b_p": 2.0
    }
  },
  "history": [
    {
      "epoch": 1,
      "batch_loss_mean": 10.438928544521332,
      "train_loss_norm": 1.961824655532837,
      "val_loss_norm": 2.124235153198242
    },
    {
      "epoch": 2,
      "batch_loss_mean": 1.8904059804402864,
      "train_loss_norm": 1.7602806091308594,
      "val_loss_norm": 1.9623537063598633
    },
    {
      "epoch": 3,
      "batch_loss_mean": 1.755720276098985,
      "train_loss_norm": 1.6649973392486572,
      "val_loss_norm": 1.8293023109436035
    },
    {
      "epoch": 4,
      "batch_loss_mean": 1.6531349558096666,
      "train_loss_norm": 1.581100344657898,
      "val_loss_norm": 1.8141331672668457
    },
    {
      "epoch": 5,
      "batch_loss_mean": 1.5726009332216704,
      "train_loss_norm": 1.63126802444458,
      "val_loss_norm": 1.9824929237365723
    },
    {
      "epoch": 6,
      "batch_loss_mean": 1.584929842215318,
      "train_loss_norm": 1.4691205024719238,
      "val_loss_norm": 1.7516162395477295
    },
    {
      "epoch": 7,
      "batch_loss_mean": 1.5381997044269855,
      "train_loss_norm": 1.4405763149261475,
      "val_loss_norm": 1.829378604888916
    },
    {
      "epoch": 8,
      "batch_loss_mean": 1.4335331504161541,
      "train_loss_norm": 1.3626928329467773,
      "val_loss_norm": 1.7869173288345337
    },
    {
      "epoch": 9,
      "batch_loss_mean": 1.3921182935054486,
      "train_loss_norm": 1.3576507568359375,
      "val_loss_norm": 1.8311879634857178
    },
    {
      "epoch": 10,
      "batch_loss_mean": 1.3962744611960192,
      "train_loss_norm": 1.3721243143081665,
      "val_loss_norm": 1.8923038244247437
    },
    {
      "epoch": 11,
      "batch_loss_mean": 1.3006588954191942,
      "train_loss_norm": 1.2123452425003052,
      "val_loss_norm": 1.8391846418380737
    },
    {
      "epoch": 12,
      "batch_loss_mean": 1.244290177638714,
      "train_loss_norm": 1.2457116842269897,
      "val_loss_norm": 1.8755534887313843
    },
    {
      "epoch": 13,
      "batch_loss_mean": 1.204898552252696,
      "train_loss_norm": 1.1479533910751343,
      "val_loss_norm": 1.86708664894104
    },
    {
      "epoch": 14,
      "batch_loss_mean": 1.1329594116944532,
      "train_loss_norm": 1.0853520631790161,
      "val_loss_norm": 1.881702184677124
    }
  ]
}